<Lifestyle_katalog_brendov_klyushki>
	<brend_klyushki name="BIG BOY">
		<model_klyushki name="FURY FX 200"></model_klyushki>
		<model_klyushki name="FURY FX 200 Long"></model_klyushki>
		<model_klyushki name="FURY FX 300"></model_klyushki>
		<model_klyushki name="FURY FX 400"></model_klyushki>
		<model_klyushki name="FURY FX 500"></model_klyushki>
		<model_klyushki name="FURY FX 600"></model_klyushki>
		<model_klyushki name="FURY FX PRO"></model_klyushki>
		<model_klyushki name="FURY FX PRO 100"></model_klyushki>
		<model_klyushki name="FURY FX PRO 100 Long"></model_klyushki>
		<model_klyushki name="FURY FX TEAM"></model_klyushki>
		<model_klyushki name="Fury FX PRO Long"></model_klyushki>
	</brend_klyushki>
	<brend_klyushki name="BRO">
		<model_klyushki name="DMG LOW"></model_klyushki>
		<model_klyushki name="DMG MID"></model_klyushki>
		<model_klyushki name="LOW PRO"></model_klyushki>
		<model_klyushki name="LOW WH"></model_klyushki>
		<model_klyushki name="MID FLEX"></model_klyushki>
		<model_klyushki name="MID PRO"></model_klyushki>
		<model_klyushki name="MID WH"></model_klyushki>
		<model_klyushki name="WOOD LOW"></model_klyushki>
		<model_klyushki name="WOOD MID"></model_klyushki>
	</brend_klyushki>
	<brend_klyushki name="Bauer">
		<model_klyushki name="AG5NT"></model_klyushki>
		<model_klyushki name="Elite"></model_klyushki>
		<model_klyushki name="GSX"></model_klyushki>
		<model_klyushki name="NSX"></model_klyushki>
		<model_klyushki name="Nexus 1000"></model_klyushki>
		<model_klyushki name="Nexus 1N"></model_klyushki>
		<model_klyushki name="Nexus 2000"></model_klyushki>
		<model_klyushki name="Nexus 2900"></model_klyushki>
		<model_klyushki name="Nexus 2N"></model_klyushki>
		<model_klyushki name="Nexus 2N PRO"></model_klyushki>
		<model_klyushki name="Nexus 2N PRO SHADOW SERIES"></model_klyushki>
		<model_klyushki name="Nexus 3N"></model_klyushki>
		<model_klyushki name="Nexus 3N PRO"></model_klyushki>
		<model_klyushki name="Nexus 400"></model_klyushki>
		<model_klyushki name="Nexus 4000"></model_klyushki>
		<model_klyushki name="Nexus 4000 LE"></model_klyushki>
		<model_klyushki name="Nexus 600"></model_klyushki>
		<model_klyushki name="Nexus 7000"></model_klyushki>
		<model_klyushki name="Nexus 8000"></model_klyushki>
		<model_klyushki name="Nexus 8000 LE"></model_klyushki>
		<model_klyushki name="Nexus ADV SERIES"></model_klyushki>
		<model_klyushki name="Nexus E3"></model_klyushki>
		<model_klyushki name="Nexus E4"></model_klyushki>
		<model_klyushki name="Nexus E40"></model_klyushki>
		<model_klyushki name="Nexus E5 PRO"></model_klyushki>
		<model_klyushki name="Nexus E50 PRO"></model_klyushki>
		<model_klyushki name="Nexus GEO"></model_klyushki>
		<model_klyushki name="Nexus League"></model_klyushki>
		<model_klyushki name="Nexus N2700"></model_klyushki>
		<model_klyushki name="Nexus N37"></model_klyushki>
		<model_klyushki name="Nexus N6000"></model_klyushki>
		<model_klyushki name="Nexus N7000"></model_klyushki>
		<model_klyushki name="Nexus N8000"></model_klyushki>
		<model_klyushki name="Nexus N9000"></model_klyushki>
		<model_klyushki name="Nexus Perfomance"></model_klyushki>
		<model_klyushki name="Nexus Sync"></model_klyushki>
		<model_klyushki name="Nexus Tracer"></model_klyushki>
		<model_klyushki name="PRODIGY"></model_klyushki>
		<model_klyushki name="PROTO"></model_klyushki>
		<model_klyushki name="Sling"></model_klyushki>
		<model_klyushki name="Supreme 0"></model_klyushki>
		<model_klyushki name="Supreme 170"></model_klyushki>
		<model_klyushki name="Supreme 1S"></model_klyushki>
		<model_klyushki name="Supreme 1S LE"></model_klyushki>
		<model_klyushki name="Supreme 2S"></model_klyushki>
		<model_klyushki name="Supreme 2S Pro"></model_klyushki>
		<model_klyushki name="Supreme 2S TEAM"></model_klyushki>
		<model_klyushki name="Supreme 3S"></model_klyushki>
		<model_klyushki name="Supreme 3S PRO"></model_klyushki>
		<model_klyushki name="Supreme ADV SERIES"></model_klyushki>
		<model_klyushki name="Supreme M5 PRO"></model_klyushki>
		<model_klyushki name="Supreme M50 PRO"></model_klyushki>
		<model_klyushki name="Supreme ONE ELIT"></model_klyushki>
		<model_klyushki name="Supreme ONE PRO 4"></model_klyushki>
		<model_klyushki name="Supreme ONE.20"></model_klyushki>
		<model_klyushki name="Supreme ONE.4"></model_klyushki>
		<model_klyushki name="Supreme ONE.7"></model_klyushki>
		<model_klyushki name="Supreme ONE.8"></model_klyushki>
		<model_klyushki name="Supreme ONE.9"></model_klyushki>
		<model_klyushki name="Supreme S170"></model_klyushki>
		<model_klyushki name="Supreme S170 LE"></model_klyushki>
		<model_klyushki name="Supreme S37"></model_klyushki>
		<model_klyushki name="Supreme STE"></model_klyushki>
		<model_klyushki name="Supreme Shadow"></model_klyushki>
		<model_klyushki name="Supreme Shadow GOAL STICK"></model_klyushki>
		<model_klyushki name="Supreme TE 4"></model_klyushki>
		<model_klyushki name="Supreme TOTALONE"></model_klyushki>
		<model_klyushki name="Supreme TOTALONE MX3"></model_klyushki>
		<model_klyushki name="Supreme TOTALONE MX3 LE"></model_klyushki>
		<model_klyushki name="Supreme TOTALONE NXG"></model_klyushki>
		<model_klyushki name="Supreme TOTALONE NXG LE"></model_klyushki>
		<model_klyushki name="Supreme Ultrasonic"></model_klyushki>
		<model_klyushki name="Vapor"></model_klyushki>
		<model_klyushki name="Vapor 1X"></model_klyushki>
		<model_klyushki name="Vapor 1X LE"></model_klyushki>
		<model_klyushki name="Vapor 1X LITE"></model_klyushki>
		<model_klyushki name="Vapor 2X"></model_klyushki>
		<model_klyushki name="Vapor 2X PRO"></model_klyushki>
		<model_klyushki name="Vapor 2X TEAM"></model_klyushki>
		<model_klyushki name="Vapor 3X"></model_klyushki>
		<model_klyushki name="Vapor 3X PRO"></model_klyushki>
		<model_klyushki name="Vapor 4X"></model_klyushki>
		<model_klyushki name="Vapor APX"></model_klyushki>
		<model_klyushki name="Vapor APX LE"></model_klyushki>
		<model_klyushki name="Vapor APX SE"></model_klyushki>
		<model_klyushki name="Vapor APX2"></model_klyushki>
		<model_klyushki name="Vapor APX2 LE"></model_klyushki>
		<model_klyushki name="Vapor FLYLITE SHADOW SERIES"></model_klyushki>
		<model_klyushki name="Vapor FlyLite"></model_klyushki>
		<model_klyushki name="Vapor Hyperlite"></model_klyushki>
		<model_klyushki name="Vapor Hyperlite 2"></model_klyushki>
		<model_klyushki name="Vapor Hyperlite GOAL STK"></model_klyushki>
		<model_klyushki name="Vapor Junior"></model_klyushki>
		<model_klyushki name="Vapor League"></model_klyushki>
		<model_klyushki name="Vapor PRODIGY"></model_klyushki>
		<model_klyushki name="Vapor TYKE"></model_klyushki>
		<model_klyushki name="Vapor X"></model_klyushki>
		<model_klyushki name="Vapor X 2.0"></model_klyushki>
		<model_klyushki name="Vapor X 4.0"></model_klyushki>
		<model_klyushki name="Vapor X 4.0 LE"></model_klyushki>
		<model_klyushki name="Vapor X 6.0"></model_klyushki>
		<model_klyushki name="Vapor X 7.0"></model_klyushki>
		<model_klyushki name="Vapor X ADVANCED"></model_klyushki>
		<model_klyushki name="Vapor X ELIT"></model_klyushki>
		<model_klyushki name="Vapor X TE"></model_klyushki>
		<model_klyushki name="Vapor X TE 2.0"></model_klyushki>
		<model_klyushki name="Vapor X.60"></model_klyushki>
		<model_klyushki name="Vapor X.70"></model_klyushki>
		<model_klyushki name="Vapor X2.5"></model_klyushki>
		<model_klyushki name="Vapor X2.7"></model_klyushki>
		<model_klyushki name="Vapor X3"></model_klyushki>
		<model_klyushki name="Vapor X3.7"></model_klyushki>
		<model_klyushki name="Vapor X4"></model_klyushki>
		<model_klyushki name="Vapor X5 PRO"></model_klyushki>
		<model_klyushki name="Vapor X600"></model_klyushki>
		<model_klyushki name="Vapor X600 LITE"></model_klyushki>
		<model_klyushki name="Vapor X700"></model_klyushki>
		<model_klyushki name="Vapor X800"></model_klyushki>
		<model_klyushki name="Vapor X900"></model_klyushki>
		<model_klyushki name="Vapor Youth"></model_klyushki>
		<model_klyushki name="X"></model_klyushki>
	</brend_klyushki>
	<brend_klyushki name="Black Stick">
		<model_klyushki name="-"></model_klyushki>
	</brend_klyushki>
	<brend_klyushki name="CCM">
		<model_klyushki name="AS5 PRO"></model_klyushki>
		<model_klyushki name="AS6 PRO"></model_klyushki>
		<model_klyushki name="C300"></model_klyushki>
		<model_klyushki name="E-Flex 3.5"></model_klyushki>
		<model_klyushki name="E-Flex 4.5"></model_klyushki>
		<model_klyushki name="E-Flex 5.5"></model_klyushki>
		<model_klyushki name="E-Flex 5.9"></model_klyushki>
		<model_klyushki name="E-Flex Pro"></model_klyushki>
		<model_klyushki name="Jetspeed"></model_klyushki>
		<model_klyushki name="Jetspeed 440"></model_klyushki>
		<model_klyushki name="Jetspeed 460"></model_klyushki>
		<model_klyushki name="Jetspeed 465"></model_klyushki>
		<model_klyushki name="Jetspeed 475"></model_klyushki>
		<model_klyushki name="Jetspeed 660"></model_klyushki>
		<model_klyushki name="Jetspeed 670"></model_klyushki>
		<model_klyushki name="Jetspeed FT"></model_klyushki>
		<model_klyushki name="Jetspeed FT Ghost"></model_klyushki>
		<model_klyushki name="Jetspeed FT TEAM"></model_klyushki>
		<model_klyushki name="Jetspeed FT2"></model_klyushki>
		<model_klyushki name="Jetspeed FT3 PRO"></model_klyushki>
		<model_klyushki name="Jetspeed FT3 TEAM"></model_klyushki>
		<model_klyushki name="Jetspeed FT4"></model_klyushki>
		<model_klyushki name="Jetspeed FT4 PRO"></model_klyushki>
		<model_klyushki name="Jetspeed FT5"></model_klyushki>
		<model_klyushki name="Jetspeed FT5 PRO"></model_klyushki>
		<model_klyushki name="Jetspeed FT6"></model_klyushki>
		<model_klyushki name="Jetspeed FT6 PRO"></model_klyushki>
		<model_klyushki name="Jetspeed FT7"></model_klyushki>
		<model_klyushki name="Jetspeed FT7 PRO"></model_klyushki>
		<model_klyushki name="Jetspeed FTW"></model_klyushki>
		<model_klyushki name="Jetspeed LE"></model_klyushki>
		<model_klyushki name="Jetspeed PRO2"></model_klyushki>
		<model_klyushki name="Jetspeed Prime"></model_klyushki>
		<model_klyushki name="Jetspeed Team"></model_klyushki>
		<model_klyushki name="LIMITED EDITION 23/24"></model_klyushki>
		<model_klyushki name="Octogun50"></model_klyushki>
		<model_klyushki name="RBZ FT1"></model_klyushki>
		<model_klyushki name="Ribcor 62K"></model_klyushki>
		<model_klyushki name="Ribcor 84K"></model_klyushki>
		<model_klyushki name="Ribcor 86K"></model_klyushki>
		<model_klyushki name="Ribcor 94K"></model_klyushki>
		<model_klyushki name="Ribcor 96K"></model_klyushki>
		<model_klyushki name="Ribcor Trigger"></model_klyushki>
		<model_klyushki name="Ribcor Trigger 2"></model_klyushki>
		<model_klyushki name="Ribcor Trigger 3D"></model_klyushki>
		<model_klyushki name="Ribcor Trigger 5"></model_klyushki>
		<model_klyushki name="Ribcor Trigger 5 PRO"></model_klyushki>
		<model_klyushki name="Ribcor Trigger 6"></model_klyushki>
		<model_klyushki name="Ribcor Trigger 6 PRO"></model_klyushki>
		<model_klyushki name="Ribcor Trigger 7"></model_klyushki>
		<model_klyushki name="Ribcor Trigger 7 PRO"></model_klyushki>
		<model_klyushki name="Ribcor Trigger 8"></model_klyushki>
		<model_klyushki name="Ribcor Trigger 8 PRO"></model_klyushki>
		<model_klyushki name="Ribcor Trigger 9"></model_klyushki>
		<model_klyushki name="Ribcor Trigger 9 PRO"></model_klyushki>
		<model_klyushki name="Ribcor Trigger 9K"></model_klyushki>
		<model_klyushki name="Ribcor Trigger PRO LE"></model_klyushki>
		<model_klyushki name="Super Tacks 9260"></model_klyushki>
		<model_klyushki name="Super Tacks 9360"></model_klyushki>
		<model_klyushki name="Super Tacks 9380"></model_klyushki>
		<model_klyushki name="Super Tacks AS-570"></model_klyushki>
		<model_klyushki name="Super Tacks AS-V PRO"></model_klyushki>
		<model_klyushki name="Super Tacks AS-VI PRO"></model_klyushki>
		<model_klyushki name="Super Tacks AS1"></model_klyushki>
		<model_klyushki name="Super Tacks AS2"></model_klyushki>
		<model_klyushki name="Super Tacks AS3"></model_klyushki>
		<model_klyushki name="Super Tacks AS3 Pro"></model_klyushki>
		<model_klyushki name="Super Tacks AS4"></model_klyushki>
		<model_klyushki name="Super Tacks AS4 PRO"></model_klyushki>
		<model_klyushki name="Super Tacks AS6 PRO"></model_klyushki>
		<model_klyushki name="Tacks"></model_klyushki>
		<model_klyushki name="Tacks 2092"></model_klyushki>
		<model_klyushki name="Tacks 4092"></model_klyushki>
		<model_klyushki name="Tacks 9040"></model_klyushki>
		<model_klyushki name="Tacks 9060"></model_klyushki>
		<model_klyushki name="Tacks 9280"></model_klyushki>
		<model_klyushki name="Tacks 9360"></model_klyushki>
		<model_klyushki name="Tacks 9380"></model_klyushki>
		<model_klyushki name="Tacks AS-V"></model_klyushki>
		<model_klyushki name="Tacks AS-V PRO"></model_klyushki>
		<model_klyushki name="Tacks AS-VI PRO"></model_klyushki>
		<model_klyushki name="U+ OCTOLITE"></model_klyushki>
		<model_klyushki name="U10"></model_klyushki>
		<model_klyushki name="U10 CL CUTURIE"></model_klyushki>
		<model_klyushki name="ULTIMATE"></model_klyushki>
	</brend_klyushki>
	<brend_klyushki name="EASTON">
		<model_klyushki name="Stealth 100S"></model_klyushki>
		<model_klyushki name="Stealth 55S"></model_klyushki>
		<model_klyushki name="Stealth 65S"></model_klyushki>
		<model_klyushki name="Stealth 75S"></model_klyushki>
		<model_klyushki name="Stealth 85S"></model_klyushki>
		<model_klyushki name="Stealth C3.0"></model_klyushki>
		<model_klyushki name="Stealth C5.0"></model_klyushki>
		<model_klyushki name="Stealth C7.0"></model_klyushki>
		<model_klyushki name="Stealth C9.0"></model_klyushki>
		<model_klyushki name="Stealth CX"></model_klyushki>
		<model_klyushki name="Stealth RS"></model_klyushki>
		<model_klyushki name="Stealth RS II"></model_klyushki>
		<model_klyushki name="Synergy 20"></model_klyushki>
		<model_klyushki name="Synergy 3S"></model_klyushki>
		<model_klyushki name="Synergy 40"></model_klyushki>
		<model_klyushki name="Synergy 60"></model_klyushki>
		<model_klyushki name="Synergy 80"></model_klyushki>
		<model_klyushki name="Synergy GX"></model_klyushki>
		<model_klyushki name="Synergy HTX"></model_klyushki>
		<model_klyushki name="Synergy SC6"></model_klyushki>
		<model_klyushki name="Synergy ST"></model_klyushki>
		<model_klyushki name="V9E"></model_klyushki>
	</brend_klyushki>
	<brend_klyushki name="Fischer">
		<model_klyushki name="CT150"></model_klyushki>
		<model_klyushki name="CT450"></model_klyushki>
		<model_klyushki name="CT750"></model_klyushki>
		<model_klyushki name="CT850"></model_klyushki>
		<model_klyushki name="CT950"></model_klyushki>
		<model_klyushki name="GF550"></model_klyushki>
		<model_klyushki name="GW150"></model_klyushki>
		<model_klyushki name="GW250"></model_klyushki>
		<model_klyushki name="HS7"></model_klyushki>
		<model_klyushki name="HX5"></model_klyushki>
		<model_klyushki name="RC One"></model_klyushki>
		<model_klyushki name="RC One IS1"></model_klyushki>
		<model_klyushki name="RC One IS2"></model_klyushki>
		<model_klyushki name="RC One IS3"></model_klyushki>
		<model_klyushki name="RC One PRO"></model_klyushki>
		<model_klyushki name="RC One XPRO"></model_klyushki>
		<model_klyushki name="Team19"></model_klyushki>
		<model_klyushki name="W150 KID"></model_klyushki>
		<model_klyushki name="W150 WOOD"></model_klyushki>
		<model_klyushki name="W250"></model_klyushki>
		<model_klyushki name="W250 ABS"></model_klyushki>
		<model_klyushki name="W250 KID"></model_klyushki>
	</brend_klyushki>
	<brend_klyushki name="Graf">
		<model_klyushki name="-"></model_klyushki>
		<model_klyushki name="Supra G-15"></model_klyushki>
		<model_klyushki name="Supra G-25"></model_klyushki>
		<model_klyushki name="Supra G-45"></model_klyushki>
		<model_klyushki name="Supra G-55"></model_klyushki>
		<model_klyushki name="Ultra G-75"></model_klyushki>
	</brend_klyushki>
	<brend_klyushki name="Grom">
		<model_klyushki name="-"></model_klyushki>
	</brend_klyushki>
	<brend_klyushki name="Inoflex">
		<model_klyushki name="Booster"></model_klyushki>
		<model_klyushki name="Ice Sense"></model_klyushki>
	</brend_klyushki>
	<brend_klyushki name="Jofa">
		<model_klyushki name="-"></model_klyushki>
	</brend_klyushki>
	<brend_klyushki name="Koho">
		<model_klyushki name="-"></model_klyushki>
		<model_klyushki name="2210"></model_klyushki>
		<model_klyushki name="Revolution"></model_klyushki>
	</brend_klyushki>
	<brend_klyushki name="Larsen">
		<model_klyushki name="Club"></model_klyushki>
		<model_klyushki name="Junior"></model_klyushki>
		<model_klyushki name="X-Force"></model_klyushki>
	</brend_klyushki>
	<brend_klyushki name="Louisville">
		<model_klyushki name="TPS Response"></model_klyushki>
		<model_klyushki name="TPS Rubber"></model_klyushki>
	</brend_klyushki>
	<brend_klyushki name="MAD GUY">
		<model_klyushki name="Ghost"></model_klyushki>
		<model_klyushki name="Hellrider"></model_klyushki>
		<model_klyushki name="Poison"></model_klyushki>
		<model_klyushki name="Prime Silver S2"></model_klyushki>
		<model_klyushki name="Strike Team"></model_klyushki>
	</brend_klyushki>
	<brend_klyushki name="Mission">
		<model_klyushki name="-"></model_klyushki>
		<model_klyushki name="L-2"></model_klyushki>
		<model_klyushki name="M-1"></model_klyushki>
	</brend_klyushki>
	<brend_klyushki name="Nordway">
		<model_klyushki name="NDW 1.0"></model_klyushki>
		<model_klyushki name="NDW 300"></model_klyushki>
		<model_klyushki name="NDW 500"></model_klyushki>
		<model_klyushki name="NDW 700"></model_klyushki>
	</brend_klyushki>
	<brend_klyushki name="OXDOG">
		<model_klyushki name="-"></model_klyushki>
	</brend_klyushki>
	<brend_klyushki name="Prime">
		<model_klyushki name="-"></model_klyushki>
		<model_klyushki name="Black Edition"></model_klyushki>
		<model_klyushki name="Limited S1"></model_klyushki>
		<model_klyushki name="Silver S2"></model_klyushki>
	</brend_klyushki>
	<brend_klyushki name="REEBOK">
		<model_klyushki name="10K"></model_klyushki>
		<model_klyushki name="16K"></model_klyushki>
		<model_klyushki name="20K"></model_klyushki>
		<model_klyushki name="4K"></model_klyushki>
		<model_klyushki name="5K"></model_klyushki>
		<model_klyushki name="6K"></model_klyushki>
		<model_klyushki name="8K"></model_klyushki>
		<model_klyushki name="A.I.3 50"></model_klyushki>
		<model_klyushki name="XT PRO"></model_klyushki>
	</brend_klyushki>
	<brend_klyushki name="RGX">
		<model_klyushki name="3010 X-CODE"></model_klyushki>
		<model_klyushki name="4010 X-CODE"></model_klyushki>
		<model_klyushki name="5010 X-CODE"></model_klyushki>
		<model_klyushki name="ENERGY 1"></model_klyushki>
		<model_klyushki name="ENERGY 2"></model_klyushki>
		<model_klyushki name="Mini"></model_klyushki>
	</brend_klyushki>
	<brend_klyushki name="SBК">
		<model_klyushki name="-"></model_klyushki>
	</brend_klyushki>
	<brend_klyushki name="SOYUZ BC">
		<model_klyushki name="ACE"></model_klyushki>
		<model_klyushki name="Ace Prime"></model_klyushki>
		<model_klyushki name="Ace prime HYPER"></model_klyushki>
		<model_klyushki name="HIT"></model_klyushki>
		<model_klyushki name="HIT START"></model_klyushki>
		<model_klyushki name="HIT ULTRA"></model_klyushki>
		<model_klyushki name="HITCH UPPER"></model_klyushki>
	</brend_klyushki>
	<brend_klyushki name="STC">
		<model_klyushki name="-"></model_klyushki>
		<model_klyushki name="2600"></model_klyushki>
		<model_klyushki name="7010"></model_klyushki>
		<model_klyushki name="MAX 1.0 KID"></model_klyushki>
		<model_klyushki name="MAX 1.5"></model_klyushki>
		<model_klyushki name="MAX 2.0"></model_klyushki>
		<model_klyushki name="Ranger"></model_klyushki>
		<model_klyushki name="Ranger 2600"></model_klyushki>
	</brend_klyushki>
	<brend_klyushki name="STX">
		<model_klyushki name="-"></model_klyushki>
		<model_klyushki name="Stallion HPR 1.1"></model_klyushki>
		<model_klyushki name="Stallon X9"></model_klyushki>
	</brend_klyushki>
	<brend_klyushki name="Salming">
		<model_klyushki name="M11 GRIP KZN OVECHKIN"></model_klyushki>
		<model_klyushki name="M17"></model_klyushki>
		<model_klyushki name="M3"></model_klyushki>
		<model_klyushki name="TORNADO"></model_klyushki>
		<model_klyushki name="TORNADO 85"></model_klyushki>
		<model_klyushki name="TORNADO SAKIC"></model_klyushki>
	</brend_klyushki>
	<brend_klyushki name="Sherwood">
		<model_klyushki name="CODE TMP3"></model_klyushki>
		<model_klyushki name="Code I"></model_klyushki>
		<model_klyushki name="Code II"></model_klyushki>
		<model_klyushki name="Code III"></model_klyushki>
		<model_klyushki name="Code IV"></model_klyushki>
		<model_klyushki name="Code V"></model_klyushki>
		<model_klyushki name="EK15"></model_klyushki>
		<model_klyushki name="EK300"></model_klyushki>
		<model_klyushki name="EK325"></model_klyushki>
		<model_klyushki name="HAVOC 100"></model_klyushki>
		<model_klyushki name="LEGEND 1"></model_klyushki>
		<model_klyushki name="LEGEND 3"></model_klyushki>
		<model_klyushki name="LEGEND 4"></model_klyushki>
		<model_klyushki name="PLAYRITE PR22"></model_klyushki>
		<model_klyushki name="Project 1"></model_klyushki>
		<model_klyushki name="Project 2"></model_klyushki>
		<model_klyushki name="Project 3"></model_klyushki>
		<model_klyushki name="Project 4"></model_klyushki>
		<model_klyushki name="Project 5"></model_klyushki>
		<model_klyushki name="Project 6"></model_klyushki>
		<model_klyushki name="Project 7"></model_klyushki>
		<model_klyushki name="Project 8"></model_klyushki>
		<model_klyushki name="Project 9"></model_klyushki>
		<model_klyushki name="Rekker M10"></model_klyushki>
		<model_klyushki name="Rekker M20"></model_klyushki>
		<model_klyushki name="Rekker M30"></model_klyushki>
		<model_klyushki name="Rekker M40"></model_klyushki>
		<model_klyushki name="Rekker M50"></model_klyushki>
		<model_klyushki name="Rekker M60"></model_klyushki>
		<model_klyushki name="Rekker M70"></model_klyushki>
		<model_klyushki name="Rekker M80"></model_klyushki>
		<model_klyushki name="Rekker M90"></model_klyushki>
		<model_klyushki name="Rekker Pro Stock"></model_klyushki>
		<model_klyushki name="T100 II"></model_klyushki>
		<model_klyushki name="T120"></model_klyushki>
		<model_klyushki name="T30 GEN II"></model_klyushki>
		<model_klyushki name="T90"></model_klyushki>
		<model_klyushki name="T90 GEN II"></model_klyushki>
		<model_klyushki name="T90 UNDER GEN II"></model_klyushki>
	</brend_klyushki>
	<brend_klyushki name="Stex">
		<model_klyushki name="-"></model_klyushki>
		<model_klyushki name="JUNIRAID 2"></model_klyushki>
		<model_klyushki name="Moroz"></model_klyushki>
		<model_klyushki name="ORANGE HAIL"></model_klyushki>
		<model_klyushki name="RAIDER 3"></model_klyushki>
	</brend_klyushki>
	<brend_klyushki name="TAC">
		<model_klyushki name="-"></model_klyushki>
	</brend_klyushki>
	<brend_klyushki name="TAMPA">
		<model_klyushki name="TEAM"></model_klyushki>
		<model_klyushki name="TEAM PRO"></model_klyushki>
	</brend_klyushki>
	<brend_klyushki name="TPS">
		<model_klyushki name="-"></model_klyushki>
		<model_klyushki name="Response R6"></model_klyushki>
		<model_klyushki name="Response R8"></model_klyushki>
	</brend_klyushki>
	<brend_klyushki name="TRUE">
		<model_klyushki name="A2.2 SBP"></model_klyushki>
		<model_klyushki name="A4.5 HT"></model_klyushki>
		<model_klyushki name="A4.5 SBP"></model_klyushki>
		<model_klyushki name="A6.0 HT"></model_klyushki>
		<model_klyushki name="A6.0 SBP"></model_klyushki>
		<model_klyushki name="AX3"></model_klyushki>
		<model_klyushki name="AX5"></model_klyushki>
		<model_klyushki name="AX7"></model_klyushki>
		<model_klyushki name="AX9"></model_klyushki>
		<model_klyushki name="Catalyst 1X"></model_klyushki>
		<model_klyushki name="Catalyst 2X"></model_klyushki>
		<model_klyushki name="Catalyst 3"></model_klyushki>
		<model_klyushki name="Catalyst 3X"></model_klyushki>
		<model_klyushki name="Catalyst 4X"></model_klyushki>
		<model_klyushki name="Catalyst 5"></model_klyushki>
		<model_klyushki name="Catalyst 5X"></model_klyushki>
		<model_klyushki name="Catalyst 7"></model_klyushki>
		<model_klyushki name="Catalyst 7X"></model_klyushki>
		<model_klyushki name="Catalyst 8X"></model_klyushki>
		<model_klyushki name="Catalyst 9"></model_klyushki>
		<model_klyushki name="Catalyst 9X"></model_klyushki>
		<model_klyushki name="Catalyst 9X3"></model_klyushki>
		<model_klyushki name="Catalyst 9X4"></model_klyushki>
		<model_klyushki name="Catalyst PX"></model_klyushki>
		<model_klyushki name="Hzrdus 3X"></model_klyushki>
		<model_klyushki name="Hzrdus 7X"></model_klyushki>
		<model_klyushki name="Hzrdus 9X"></model_klyushki>
		<model_klyushki name="Hzrdus PX"></model_klyushki>
	</brend_klyushki>
	<brend_klyushki name="Tackla">
		<model_klyushki name="-"></model_klyushki>
		<model_klyushki name="Advantage"></model_klyushki>
		<model_klyushki name="Pro 3000 NHL"></model_klyushki>
	</brend_klyushki>
	<brend_klyushki name="Tisa">
		<model_klyushki name="Elita"></model_klyushki>
		<model_klyushki name="Master"></model_klyushki>
	</brend_klyushki>
	<brend_klyushki name="Torspo">
		<model_klyushki name="-"></model_klyushki>
		<model_klyushki name="Surge 221"></model_klyushki>
		<model_klyushki name="Surge 421"></model_klyushki>
		<model_klyushki name="Surge 521"></model_klyushki>
		<model_klyushki name="Velocity 8000"></model_klyushki>
	</brend_klyushki>
	<brend_klyushki name="Vikkela">
		<model_klyushki name="GR8"></model_klyushki>
		<model_klyushki name="GR8 GG"></model_klyushki>
		<model_klyushki name="GR8 GRIP"></model_klyushki>
		<model_klyushki name="GR8 NMG"></model_klyushki>
		<model_klyushki name="ViG"></model_klyushki>
		<model_klyushki name="ViG NMG"></model_klyushki>
		<model_klyushki name="ZAG"></model_klyushki>
		<model_klyushki name="ZAG GG"></model_klyushki>
		<model_klyushki name="ZAG GRIP"></model_klyushki>
		<model_klyushki name="ZAG II"></model_klyushki>
		<model_klyushki name="ZAG II GG"></model_klyushki>
		<model_klyushki name="ZAG II GRIP"></model_klyushki>
		<model_klyushki name="ZAG II NMG"></model_klyushki>
		<model_klyushki name="ZAG NMG"></model_klyushki>
		<model_klyushki name="ZERO.31"></model_klyushki>
	</brend_klyushki>
	<brend_klyushki name="VАLL">
		<model_klyushki name="-"></model_klyushki>
	</brend_klyushki>
	<brend_klyushki name="Warrior">
		<model_klyushki name="Alpha DX"></model_klyushki>
		<model_klyushki name="Alpha DX3"></model_klyushki>
		<model_klyushki name="Alpha DX30"></model_klyushki>
		<model_klyushki name="Alpha DX4"></model_klyushki>
		<model_klyushki name="Alpha DX5"></model_klyushki>
		<model_klyushki name="Alpha LX 20"></model_klyushki>
		<model_klyushki name="Alpha LX 30"></model_klyushki>
		<model_klyushki name="Alpha LX 50"></model_klyushki>
		<model_klyushki name="Alpha LX PRO"></model_klyushki>
		<model_klyushki name="Alpha LX PRO Tyke"></model_klyushki>
		<model_klyushki name="Alpha LX2"></model_klyushki>
		<model_klyushki name="Alpha LX2 PRO"></model_klyushki>
		<model_klyushki name="Alpha LX2 STRIKE"></model_klyushki>
		<model_klyushki name="Alpha LX2 Tyke"></model_klyushki>
		<model_klyushki name="Alpha QX"></model_klyushki>
		<model_klyushki name="Alpha QX3"></model_klyushki>
		<model_klyushki name="Alpha QX4"></model_klyushki>
		<model_klyushki name="Alpha QX5"></model_klyushki>
		<model_klyushki name="Covert QR5 20"></model_klyushki>
		<model_klyushki name="Covert QR5 30"></model_klyushki>
		<model_klyushki name="Covert QR5 40"></model_klyushki>
		<model_klyushki name="Covert QR5 50"></model_klyushki>
		<model_klyushki name="Covert QR5 PRO"></model_klyushki>
		<model_klyushki name="Covert QR5 PRO Tyke"></model_klyushki>
		<model_klyushki name="Covert QR6"></model_klyushki>
		<model_klyushki name="Covert QR6 20"></model_klyushki>
		<model_klyushki name="Covert QR6 40"></model_klyushki>
		<model_klyushki name="Covert QR6 50"></model_klyushki>
		<model_klyushki name="Covert QR6 PRO"></model_klyushki>
		<model_klyushki name="Covert QR6 REV"></model_klyushki>
		<model_klyushki name="Covert QRE"></model_klyushki>
		<model_klyushki name="Covert QRE 10"></model_klyushki>
		<model_klyushki name="Covert QRE 20 PRO"></model_klyushki>
		<model_klyushki name="Covert QRE 4"></model_klyushki>
		<model_klyushki name="Covert QRE 40"></model_klyushki>
		<model_klyushki name="Covert QRE 5"></model_klyushki>
		<model_klyushki name="Covert QRE 5 PRO"></model_klyushki>
		<model_klyushki name="Covert QRE 50"></model_klyushki>
		<model_klyushki name="Covert QRE 60"></model_klyushki>
		<model_klyushki name="Covert QRE PRO TEAM"></model_klyushki>
		<model_klyushki name="Covert QRE Pro T1"></model_klyushki>
		<model_klyushki name="Covert QRE3"></model_klyushki>
		<model_klyushki name="Covert QRE4"></model_klyushki>
		<model_klyushki name="Covert QRL Pro"></model_klyushki>
		<model_klyushki name="Novium"></model_klyushki>
		<model_klyushki name="Novium PRO"></model_klyushki>
		<model_klyushki name="Novium SP"></model_klyushki>
		<model_klyushki name="QXT"></model_klyushki>
		<model_klyushki name="Rise"></model_klyushki>
		<model_klyushki name="Rise Tyke"></model_klyushki>
		<model_klyushki name="SUPER NOVIUM"></model_klyushki>
		<model_klyushki name="Swagger STR2"></model_klyushki>
	</brend_klyushki>
	<brend_klyushki name="Без бренда (NoName)">
		<model_klyushki name="-"></model_klyushki>
	</brend_klyushki>
	<brend_klyushki name="Другой">
		<model_klyushki name="-"></model_klyushki>
	</brend_klyushki>
	<brend_klyushki name="ЗаряД">
		<model_klyushki name="A Dex"></model_klyushki>
		<model_klyushki name="A PRO"></model_klyushki>
		<model_klyushki name="A3"></model_klyushki>
		<model_klyushki name="A47"></model_klyushki>
		<model_klyushki name="A50"></model_klyushki>
		<model_klyushki name="A7"></model_klyushki>
		<model_klyushki name="AК12"></model_klyushki>
		<model_klyushki name="AК47"></model_klyushki>
		<model_klyushki name="AК47 TEAM"></model_klyushki>
		<model_klyushki name="AК50"></model_klyushki>
		<model_klyushki name="AК9"></model_klyushki>
		<model_klyushki name="C PRO"></model_klyushki>
		<model_klyushki name="C20"></model_klyushki>
		<model_klyushki name="C30"></model_klyushki>
		<model_klyushki name="C40"></model_klyushki>
		<model_klyushki name="C400"></model_klyushki>
		<model_klyushki name="C50"></model_klyushki>
		<model_klyushki name="C500"></model_klyushki>
		<model_klyushki name="T PRO"></model_klyushki>
		<model_klyushki name="T10"></model_klyushki>
		<model_klyushki name="T100"></model_klyushki>
		<model_klyushki name="T5"></model_klyushki>
		<model_klyushki name="T7"></model_klyushki>
		<model_klyushki name="T72"></model_klyushki>
		<model_klyushki name="T72-III"></model_klyushki>
		<model_klyushki name="T9"></model_klyushki>
		<model_klyushki name="T90"></model_klyushki>
		<model_klyushki name="T90 TEAM"></model_klyushki>
		<model_klyushki name="T90-III"></model_klyushki>
		<model_klyushki name="Мастер"></model_klyushki>
	</brend_klyushki>
	<brend_klyushki name="Соболь">
		<model_klyushki name="-"></model_klyushki>
	</brend_klyushki>
</Lifestyle_katalog_brendov_klyushki>