<?xml version="1.0" encoding="UTF-8"?>
<DryerDewPointValues>
	<DryerDewPoint>-70</DryerDewPoint>
	<DryerDewPoint>-69</DryerDewPoint>
	<DryerDewPoint>-68</DryerDewPoint>
	<DryerDewPoint>-67</DryerDewPoint>
	<DryerDewPoint>-66</DryerDewPoint>
	<DryerDewPoint>-65</DryerDewPoint>
	<DryerDewPoint>-64</DryerDewPoint>
	<DryerDewPoint>-63</DryerDewPoint>
	<DryerDewPoint>-62</DryerDewPoint>
	<DryerDewPoint>-61</DryerDewPoint>
	<DryerDewPoint>-60</DryerDewPoint>
	<DryerDewPoint>-59</DryerDewPoint>
	<DryerDewPoint>-58</DryerDewPoint>
	<DryerDewPoint>-57</DryerDewPoint>
	<DryerDewPoint>-56</DryerDewPoint>
	<DryerDewPoint>-55</DryerDewPoint>
	<DryerDewPoint>-54</DryerDewPoint>
	<DryerDewPoint>-53</DryerDewPoint>
	<DryerDewPoint>-52</DryerDewPoint>
	<DryerDewPoint>-51</DryerDewPoint>
	<DryerDewPoint>-50</DryerDewPoint>
	<DryerDewPoint>-49</DryerDewPoint>
	<DryerDewPoint>-48</DryerDewPoint>
	<DryerDewPoint>-47</DryerDewPoint>
	<DryerDewPoint>-46</DryerDewPoint>
	<DryerDewPoint>-45</DryerDewPoint>
	<DryerDewPoint>-44</DryerDewPoint>
	<DryerDewPoint>-43</DryerDewPoint>
	<DryerDewPoint>-42</DryerDewPoint>
	<DryerDewPoint>-41</DryerDewPoint>
	<DryerDewPoint>-40</DryerDewPoint>
	<DryerDewPoint>-39</DryerDewPoint>
	<DryerDewPoint>-38</DryerDewPoint>
	<DryerDewPoint>-37</DryerDewPoint>
	<DryerDewPoint>-36</DryerDewPoint>
	<DryerDewPoint>-35</DryerDewPoint>
	<DryerDewPoint>-34</DryerDewPoint>
	<DryerDewPoint>-33</DryerDewPoint>
	<DryerDewPoint>-32</DryerDewPoint>
	<DryerDewPoint>-31</DryerDewPoint>
	<DryerDewPoint>-30</DryerDewPoint>
	<DryerDewPoint>-29</DryerDewPoint>
	<DryerDewPoint>-28</DryerDewPoint>
	<DryerDewPoint>-27</DryerDewPoint>
	<DryerDewPoint>-26</DryerDewPoint>
	<DryerDewPoint>-25</DryerDewPoint>
	<DryerDewPoint>-24</DryerDewPoint>
	<DryerDewPoint>-23</DryerDewPoint>
	<DryerDewPoint>-22</DryerDewPoint>
	<DryerDewPoint>-21</DryerDewPoint>
	<DryerDewPoint>-20</DryerDewPoint>
	<DryerDewPoint>-19</DryerDewPoint>
	<DryerDewPoint>-18</DryerDewPoint>
	<DryerDewPoint>-17</DryerDewPoint>
	<DryerDewPoint>-16</DryerDewPoint>
	<DryerDewPoint>-15</DryerDewPoint>
	<DryerDewPoint>-14</DryerDewPoint>
	<DryerDewPoint>-13</DryerDewPoint>
	<DryerDewPoint>-12</DryerDewPoint>
	<DryerDewPoint>-11</DryerDewPoint>
	<DryerDewPoint>-10</DryerDewPoint>
	<DryerDewPoint>-9</DryerDewPoint>
	<DryerDewPoint>-8</DryerDewPoint>
	<DryerDewPoint>-7</DryerDewPoint>
	<DryerDewPoint>-6</DryerDewPoint>
	<DryerDewPoint>-5</DryerDewPoint>
	<DryerDewPoint>-4</DryerDewPoint>
	<DryerDewPoint>-3</DryerDewPoint>
	<DryerDewPoint>-2</DryerDewPoint>
	<DryerDewPoint>-1</DryerDewPoint>
	<DryerDewPoint>0</DryerDewPoint>
	<DryerDewPoint>+1</DryerDewPoint>
	<DryerDewPoint>+2</DryerDewPoint>
	<DryerDewPoint>+3</DryerDewPoint>
	<DryerDewPoint>+4</DryerDewPoint>
	<DryerDewPoint>+5</DryerDewPoint>
	<DryerDewPoint>+6</DryerDewPoint>
	<DryerDewPoint>+7</DryerDewPoint>
	<DryerDewPoint>+8</DryerDewPoint>
	<DryerDewPoint>+9</DryerDewPoint>
	<DryerDewPoint>+10</DryerDewPoint>
</DryerDewPointValues>
