<Keramogranit>
	<brend_keramogranita name="41zero42"></brend_keramogranita>
	<brend_keramogranita name="A-Ceramica"></brend_keramogranita>
	<brend_keramogranita name="ABK Ceramiche"></brend_keramogranita>
	<brend_keramogranita name="ADEX"></brend_keramogranita>
	<brend_keramogranita name="AGL Tiles"></brend_keramogranita>
	<brend_keramogranita name="APE Ceramica"></brend_keramogranita>
	<brend_keramogranita name="AVA Ceramica"></brend_keramogranita>
	<brend_keramogranita name="Absolut Gres"></brend_keramogranita>
	<brend_keramogranita name="Absolut Keramika"></brend_keramogranita>
	<brend_keramogranita name="Age Art"></brend_keramogranita>
	<brend_keramogranita name="Alaplana"></brend_keramogranita>
	<brend_keramogranita name="Alma Ceramica"></brend_keramogranita>
	<brend_keramogranita name="Alpas Cera"></brend_keramogranita>
	<brend_keramogranita name="Altacera"></brend_keramogranita>
	<brend_keramogranita name="Ametis"></brend_keramogranita>
	<brend_keramogranita name="Amin Tile Co."></brend_keramogranita>
	<brend_keramogranita name="Aparici"></brend_keramogranita>
	<brend_keramogranita name="Apavisa"></brend_keramogranita>
	<brend_keramogranita name="Arcadia Ceramica"></brend_keramogranita>
	<brend_keramogranita name="Arcana Ceramica"></brend_keramogranita>
	<brend_keramogranita name="Argenta"></brend_keramogranita>
	<brend_keramogranita name="Ariana"></brend_keramogranita>
	<brend_keramogranita name="Ariostea"></brend_keramogranita>
	<brend_keramogranita name="Art Ceramic"></brend_keramogranita>
	<brend_keramogranita name="Art&amp;Natura Ceramic"></brend_keramogranita>
	<brend_keramogranita name="Artcer"></brend_keramogranita>
	<brend_keramogranita name="Artens"></brend_keramogranita>
	<brend_keramogranita name="Ascale"></brend_keramogranita>
	<brend_keramogranita name="Ascot Ceramiche"></brend_keramogranita>
	<brend_keramogranita name="Atlas Concorde"></brend_keramogranita>
	<brend_keramogranita name="Atrivm"></brend_keramogranita>
	<brend_keramogranita name="Axima"></brend_keramogranita>
	<brend_keramogranita name="Azario"></brend_keramogranita>
	<brend_keramogranita name="Azori"></brend_keramogranita>
	<brend_keramogranita name="Azteca"></brend_keramogranita>
	<brend_keramogranita name="Azulejos Benadresa"></brend_keramogranita>
	<brend_keramogranita name="Azulejos Borja"></brend_keramogranita>
	<brend_keramogranita name="Azulev"></brend_keramogranita>
	<brend_keramogranita name="Azuvi"></brend_keramogranita>
	<brend_keramogranita name="Baldocer"></brend_keramogranita>
	<brend_keramogranita name="Basconi Home"></brend_keramogranita>
	<brend_keramogranita name="Belani"></brend_keramogranita>
	<brend_keramogranita name="Beryoza Ceramica"></brend_keramogranita>
	<brend_keramogranita name="Bien"></brend_keramogranita>
	<brend_keramogranita name="Bluezone"></brend_keramogranita>
	<brend_keramogranita name="Bode Ceramica"></brend_keramogranita>
	<brend_keramogranita name="Bonaparte"></brend_keramogranita>
	<brend_keramogranita name="Brennero Ceramiche"></brend_keramogranita>
	<brend_keramogranita name="CE.SI."></brend_keramogranita>
	<brend_keramogranita name="CF-Systems"></brend_keramogranita>
	<brend_keramogranita name="CIR Ceramiche"></brend_keramogranita>
	<brend_keramogranita name="Caesar Ceramiche"></brend_keramogranita>
	<brend_keramogranita name="Carmen"></brend_keramogranita>
	<brend_keramogranita name="Casa Dolce Casa"></brend_keramogranita>
	<brend_keramogranita name="Casalgrande Padana"></brend_keramogranita>
	<brend_keramogranita name="Cayyenne Ceramiche"></brend_keramogranita>
	<brend_keramogranita name="Century"></brend_keramogranita>
	<brend_keramogranita name="Ceracasa"></brend_keramogranita>
	<brend_keramogranita name="Ceradim"></brend_keramogranita>
	<brend_keramogranita name="Ceramente Stellare"></brend_keramogranita>
	<brend_keramogranita name="Ceramica Classic"></brend_keramogranita>
	<brend_keramogranita name="Ceramiche Brennero"></brend_keramogranita>
	<brend_keramogranita name="Ceranosa-Goldencer"></brend_keramogranita>
	<brend_keramogranita name="Cercom Ceramiche"></brend_keramogranita>
	<brend_keramogranita name="Cerdomus"></brend_keramogranita>
	<brend_keramogranita name="Cerim"></brend_keramogranita>
	<brend_keramogranita name="Cersanit"></brend_keramogranita>
	<brend_keramogranita name="Cicogres"></brend_keramogranita>
	<brend_keramogranita name="Cifre Ceramica"></brend_keramogranita>
	<brend_keramogranita name="City"></brend_keramogranita>
	<brend_keramogranita name="Codicer"></brend_keramogranita>
	<brend_keramogranita name="ColiseumGres"></brend_keramogranita>
	<brend_keramogranita name="Colli Ceramica"></brend_keramogranita>
	<brend_keramogranita name="Colorker"></brend_keramogranita>
	<brend_keramogranita name="Colortile"></brend_keramogranita>
	<brend_keramogranita name="Concor"></brend_keramogranita>
	<brend_keramogranita name="Cotto Petrus"></brend_keramogranita>
	<brend_keramogranita name="Coverlam"></brend_keramogranita>
	<brend_keramogranita name="Creo Ceramque"></brend_keramogranita>
	<brend_keramogranita name="Creto"></brend_keramogranita>
	<brend_keramogranita name="Cube Ceramica"></brend_keramogranita>
	<brend_keramogranita name="Culto"></brend_keramogranita>
	<brend_keramogranita name="DNA Tiles"></brend_keramogranita>
	<brend_keramogranita name="DO&amp;PO"></brend_keramogranita>
	<brend_keramogranita name="Dado Ceramica"></brend_keramogranita>
	<brend_keramogranita name="Dako"></brend_keramogranita>
	<brend_keramogranita name="Decocer"></brend_keramogranita>
	<brend_keramogranita name="Decovita"></brend_keramogranita>
	<brend_keramogranita name="Del Conca"></brend_keramogranita>
	<brend_keramogranita name="Delacora"></brend_keramogranita>
	<brend_keramogranita name="Domino"></brend_keramogranita>
	<brend_keramogranita name="Dual Gres"></brend_keramogranita>
	<brend_keramogranita name="Dune"></brend_keramogranita>
	<brend_keramogranita name="Dvomo"></brend_keramogranita>
	<brend_keramogranita name="Ecoceramic"></brend_keramogranita>
	<brend_keramogranita name="Ecogres"></brend_keramogranita>
	<brend_keramogranita name="EdimaxAstor"></brend_keramogranita>
	<brend_keramogranita name="Eefa"></brend_keramogranita>
	<brend_keramogranita name="El Barco"></brend_keramogranita>
	<brend_keramogranita name="El Molino"></brend_keramogranita>
	<brend_keramogranita name="Elios/Exelle"></brend_keramogranita>
	<brend_keramogranita name="Emigres"></brend_keramogranita>
	<brend_keramogranita name="EnergieKer"></brend_keramogranita>
	<brend_keramogranita name="Ennface"></brend_keramogranita>
	<brend_keramogranita name="Enping Jingye Ceramic"></brend_keramogranita>
	<brend_keramogranita name="Equipe Ceramicas"></brend_keramogranita>
	<brend_keramogranita name="Estima Ceramica"></brend_keramogranita>
	<brend_keramogranita name="Eternal"></brend_keramogranita>
	<brend_keramogranita name="Etile"></brend_keramogranita>
	<brend_keramogranita name="Exagres"></brend_keramogranita>
	<brend_keramogranita name="FAP Ceramiche"></brend_keramogranita>
	<brend_keramogranita name="FMG Marmi e Graniti"></brend_keramogranita>
	<brend_keramogranita name="Fakhar"></brend_keramogranita>
	<brend_keramogranita name="Fanal"></brend_keramogranita>
	<brend_keramogranita name="Fioranese"></brend_keramogranita>
	<brend_keramogranita name="Flais Granito"></brend_keramogranita>
	<brend_keramogranita name="Flaviker"></brend_keramogranita>
	<brend_keramogranita name="Floor"></brend_keramogranita>
	<brend_keramogranita name="Floor Gres"></brend_keramogranita>
	<brend_keramogranita name="Fondovalle"></brend_keramogranita>
	<brend_keramogranita name="Francisco Segarra"></brend_keramogranita>
	<brend_keramogranita name="Gambini"></brend_keramogranita>
	<brend_keramogranita name="Gardenia Orchidea"></brend_keramogranita>
	<brend_keramogranita name="Gayafores"></brend_keramogranita>
	<brend_keramogranita name="Geotiles"></brend_keramogranita>
	<brend_keramogranita name="GlobalTile"></brend_keramogranita>
	<brend_keramogranita name="Globus Ceramica"></brend_keramogranita>
	<brend_keramogranita name="Golden Tile"></brend_keramogranita>
	<brend_keramogranita name="Goldis Tile"></brend_keramogranita>
	<brend_keramogranita name="Gracia Ceramica"></brend_keramogranita>
	<brend_keramogranita name="Graniser"></brend_keramogranita>
	<brend_keramogranita name="Graniti Fiandre"></brend_keramogranita>
	<brend_keramogranita name="Granoland"></brend_keramogranita>
	<brend_keramogranita name="Grasaro"></brend_keramogranita>
	<brend_keramogranita name="Gravita"></brend_keramogranita>
	<brend_keramogranita name="Grazia Ceramiche"></brend_keramogranita>
	<brend_keramogranita name="Graсia Ceramica"></brend_keramogranita>
	<brend_keramogranita name="Gresan"></brend_keramogranita>
	<brend_keramogranita name="Gresmanc"></brend_keramogranita>
	<brend_keramogranita name="Grespania"></brend_keramogranita>
	<brend_keramogranita name="Gresse"></brend_keramogranita>
	<brend_keramogranita name="Halcon Ceramicas"></brend_keramogranita>
	<brend_keramogranita name="Harmony"></brend_keramogranita>
	<brend_keramogranita name="ITC"></brend_keramogranita>
	<brend_keramogranita name="ITT Ceramic"></brend_keramogranita>
	<brend_keramogranita name="Ibero Ceramicas"></brend_keramogranita>
	<brend_keramogranita name="Idalgo"></brend_keramogranita>
	<brend_keramogranita name="Imola Ceramica"></brend_keramogranita>
	<brend_keramogranita name="Incolor"></brend_keramogranita>
	<brend_keramogranita name="Infiniti"></brend_keramogranita>
	<brend_keramogranita name="InterCerama"></brend_keramogranita>
	<brend_keramogranita name="Iris Ceramica"></brend_keramogranita>
	<brend_keramogranita name="Italgraniti"></brend_keramogranita>
	<brend_keramogranita name="Italica"></brend_keramogranita>
	<brend_keramogranita name="Italon"></brend_keramogranita>
	<brend_keramogranita name="Jano Tiles"></brend_keramogranita>
	<brend_keramogranita name="KEOPE Ceramiche"></brend_keramogranita>
	<brend_keramogranita name="Kale"></brend_keramogranita>
	<brend_keramogranita name="Keraben"></brend_keramogranita>
	<brend_keramogranita name="Kerald"></brend_keramogranita>
	<brend_keramogranita name="Kerama Marazzi"></brend_keramogranita>
	<brend_keramogranita name="Keramark"></brend_keramogranita>
	<brend_keramogranita name="Keratile-KTL"></brend_keramogranita>
	<brend_keramogranita name="Kerlife"></brend_keramogranita>
	<brend_keramogranita name="Kerlite"></brend_keramogranita>
	<brend_keramogranita name="Keros Ceramica"></brend_keramogranita>
	<brend_keramogranita name="Kerranova"></brend_keramogranita>
	<brend_keramogranita name="Kevis"></brend_keramogranita>
	<brend_keramogranita name="Kreaforta"></brend_keramogranita>
	<brend_keramogranita name="Kronos Ceramiche"></brend_keramogranita>
	<brend_keramogranita name="Kutahya"></brend_keramogranita>
	<brend_keramogranita name="LB Ceramics"></brend_keramogranita>
	<brend_keramogranita name="LCM"></brend_keramogranita>
	<brend_keramogranita name="LEA Ceramiche"></brend_keramogranita>
	<brend_keramogranita name="LV Granito"></brend_keramogranita>
	<brend_keramogranita name="La Fabbrica"></brend_keramogranita>
	<brend_keramogranita name="La Faenza"></brend_keramogranita>
	<brend_keramogranita name="La Fenice"></brend_keramogranita>
	<brend_keramogranita name="La Platera"></brend_keramogranita>
	<brend_keramogranita name="Lamborghini Tonino"></brend_keramogranita>
	<brend_keramogranita name="Laminam"></brend_keramogranita>
	<brend_keramogranita name="Land Porcelanico"></brend_keramogranita>
	<brend_keramogranita name="Laparet"></brend_keramogranita>
	<brend_keramogranita name="Lasselsberger Ceramics"></brend_keramogranita>
	<brend_keramogranita name="Lavelly"></brend_keramogranita>
	<brend_keramogranita name="Ldecor"></brend_keramogranita>
	<brend_keramogranita name="LeeDo &amp; Caramelle"></brend_keramogranita>
	<brend_keramogranita name="Leopard"></brend_keramogranita>
	<brend_keramogranita name="Lightgres"></brend_keramogranita>
	<brend_keramogranita name="Living Ceramics"></brend_keramogranita>
	<brend_keramogranita name="Love Tiles"></brend_keramogranita>
	<brend_keramogranita name="Maimoon Ceramica"></brend_keramogranita>
	<brend_keramogranita name="Mainzu"></brend_keramogranita>
	<brend_keramogranita name="Majorca Tiffany"></brend_keramogranita>
	<brend_keramogranita name="Marazzi Italy"></brend_keramogranita>
	<brend_keramogranita name="Marca Corona"></brend_keramogranita>
	<brend_keramogranita name="Marmocer"></brend_keramogranita>
	<brend_keramogranita name="Mei"></brend_keramogranita>
	<brend_keramogranita name="Meissen Keramik"></brend_keramogranita>
	<brend_keramogranita name="Mirage"></brend_keramogranita>
	<brend_keramogranita name="Mito"></brend_keramogranita>
	<brend_keramogranita name="Monalisa"></brend_keramogranita>
	<brend_keramogranita name="Monocibec"></brend_keramogranita>
	<brend_keramogranita name="Monopole Ceramica"></brend_keramogranita>
	<brend_keramogranita name="Moreroom"></brend_keramogranita>
	<brend_keramogranita name="Museum"></brend_keramogranita>
	<brend_keramogranita name="Muzzi"></brend_keramogranita>
	<brend_keramogranita name="Mykonos"></brend_keramogranita>
	<brend_keramogranita name="NSMosaic"></brend_keramogranita>
	<brend_keramogranita name="NT Ceramic"></brend_keramogranita>
	<brend_keramogranita name="Nanogress"></brend_keramogranita>
	<brend_keramogranita name="Navarti"></brend_keramogranita>
	<brend_keramogranita name="Naxos Ceramica"></brend_keramogranita>
	<brend_keramogranita name="Neodom"></brend_keramogranita>
	<brend_keramogranita name="New Tiles"></brend_keramogranita>
	<brend_keramogranita name="New Trend"></brend_keramogranita>
	<brend_keramogranita name="Novabell"></brend_keramogranita>
	<brend_keramogranita name="Novin Ceram"></brend_keramogranita>
	<brend_keramogranita name="Ocean Ceramic"></brend_keramogranita>
	<brend_keramogranita name="OnlyGres"></brend_keramogranita>
	<brend_keramogranita name="Orinda"></brend_keramogranita>
	<brend_keramogranita name="Oset"></brend_keramogranita>
	<brend_keramogranita name="Pamesa Ceramica"></brend_keramogranita>
	<brend_keramogranita name="Pardis Ceramic Pazh"></brend_keramogranita>
	<brend_keramogranita name="Peronda Ceramicas"></brend_keramogranita>
	<brend_keramogranita name="Piemme Ceramiche"></brend_keramogranita>
	<brend_keramogranita name="PiezaROSA"></brend_keramogranita>
	<brend_keramogranita name="Polo Gres"></brend_keramogranita>
	<brend_keramogranita name="Porcela Bobo"></brend_keramogranita>
	<brend_keramogranita name="Porcelaingres"></brend_keramogranita>
	<brend_keramogranita name="Porcelanicos HDC"></brend_keramogranita>
	<brend_keramogranita name="Porcelanite Dos"></brend_keramogranita>
	<brend_keramogranita name="Porcelanosa"></brend_keramogranita>
	<brend_keramogranita name="Primavera"></brend_keramogranita>
	<brend_keramogranita name="Prime Ceramics"></brend_keramogranita>
	<brend_keramogranita name="Prissmacer"></brend_keramogranita>
	<brend_keramogranita name="ProGres"></brend_keramogranita>
	<brend_keramogranita name="Progress"></brend_keramogranita>
	<brend_keramogranita name="QUA"></brend_keramogranita>
	<brend_keramogranita name="Quadro Decor"></brend_keramogranita>
	<brend_keramogranita name="RAK Ceramics"></brend_keramogranita>
	<brend_keramogranita name="REX Ceramiche"></brend_keramogranita>
	<brend_keramogranita name="Ragno"></brend_keramogranita>
	<brend_keramogranita name="Realonda Ceramica"></brend_keramogranita>
	<brend_keramogranita name="Refin"></brend_keramogranita>
	<brend_keramogranita name="Revoir Paris"></brend_keramogranita>
	<brend_keramogranita name="Rialto"></brend_keramogranita>
	<brend_keramogranita name="Ribesalbes"></brend_keramogranita>
	<brend_keramogranita name="Roberto Cavalli"></brend_keramogranita>
	<brend_keramogranita name="Roca"></brend_keramogranita>
	<brend_keramogranita name="Rocersa"></brend_keramogranita>
	<brend_keramogranita name="Rondine Group RHS"></brend_keramogranita>
	<brend_keramogranita name="Rossacera"></brend_keramogranita>
	<brend_keramogranita name="Royce"></brend_keramogranita>
	<brend_keramogranita name="STN Ceramica"></brend_keramogranita>
	<brend_keramogranita name="Saime Ceramiche"></brend_keramogranita>
	<brend_keramogranita name="Saloni Ceramica"></brend_keramogranita>
	<brend_keramogranita name="Sanamero"></brend_keramogranita>
	<brend_keramogranita name="Sanchis Home"></brend_keramogranita>
	<brend_keramogranita name="Sant Agostino"></brend_keramogranita>
	<brend_keramogranita name="Serenissima"></brend_keramogranita>
	<brend_keramogranita name="SilverFox"></brend_keramogranita>
	<brend_keramogranita name="Simpolo"></brend_keramogranita>
	<brend_keramogranita name="Staro"></brend_keramogranita>
	<brend_keramogranita name="Steppe Ceramics"></brend_keramogranita>
	<brend_keramogranita name="Stiles Ceramic"></brend_keramogranita>
	<brend_keramogranita name="Stone4home"></brend_keramogranita>
	<brend_keramogranita name="Supergres Ceramiche"></brend_keramogranita>
	<brend_keramogranita name="Surface Lab"></brend_keramogranita>
	<brend_keramogranita name="Tagina"></brend_keramogranita>
	<brend_keramogranita name="Tau Ceramica"></brend_keramogranita>
	<brend_keramogranita name="Tilekraft"></brend_keramogranita>
	<brend_keramogranita name="TopCer"></brend_keramogranita>
	<brend_keramogranita name="Tuscania Ceramiche"></brend_keramogranita>
	<brend_keramogranita name="Unitile"></brend_keramogranita>
	<brend_keramogranita name="Urbatek"></brend_keramogranita>
	<brend_keramogranita name="Usak Seramik"></brend_keramogranita>
	<brend_keramogranita name="Vallelunga Ceramica"></brend_keramogranita>
	<brend_keramogranita name="Varmora"></brend_keramogranita>
	<brend_keramogranita name="Velsaa"></brend_keramogranita>
	<brend_keramogranita name="Venatto"></brend_keramogranita>
	<brend_keramogranita name="Venis"></brend_keramogranita>
	<brend_keramogranita name="Versace"></brend_keramogranita>
	<brend_keramogranita name="Villeroy &amp; Boch"></brend_keramogranita>
	<brend_keramogranita name="Vitacer"></brend_keramogranita>
	<brend_keramogranita name="Vitra"></brend_keramogranita>
	<brend_keramogranita name="Vives Ceramica"></brend_keramogranita>
	<brend_keramogranita name="WOW"></brend_keramogranita>
	<brend_keramogranita name="XLight"></brend_keramogranita>
	<brend_keramogranita name="Yurtbay"></brend_keramogranita>
	<brend_keramogranita name="ZYX"></brend_keramogranita>
	<brend_keramogranita name="Zibo Fusure"></brend_keramogranita>
	<brend_keramogranita name="Без бренда"></brend_keramogranita>
	<brend_keramogranita name="Вива"></brend_keramogranita>
	<brend_keramogranita name="Грани Таганая"></brend_keramogranita>
	<brend_keramogranita name="Гранитея"></brend_keramogranita>
	<brend_keramogranita name="Квадро Декор"></brend_keramogranita>
	<brend_keramogranita name="Керамика Будущего"></brend_keramogranita>
	<brend_keramogranita name="Керамин"></brend_keramogranita>
	<brend_keramogranita name="Керамопро"></brend_keramogranita>
	<brend_keramogranita name="Керлайф"></brend_keramogranita>
	<brend_keramogranita name="М-Квадрат"></brend_keramogranita>
	<brend_keramogranita name="Нефрит-Керамика"></brend_keramogranita>
	<brend_keramogranita name="Топ Рус"></brend_keramogranita>
	<brend_keramogranita name="Уральский Гранит"></brend_keramogranita>
	<brend_keramogranita name="Шахтинская плитка"></brend_keramogranita>
</Keramogranit>