<Optika_i_snaryazhenie>
	<brand name="Arkon"></brand>
	<brand name="Bushnell"></brand>
	<brand name="Guide"></brand>
	<brand name="Hawke"></brand>
	<brand name="Helios"></brand>
	<brand name="Holosun"></brand>
	<brand name="Leapers"></brand>
	<brand name="Leupold"></brand>
	<brand name="Levenhuk"></brand>
	<brand name="MewLite"></brand>
	<brand name="Nikon"></brand>
	<brand name="Veber"></brand>
	<brand name="Vector Optics"></brand>
	<brand name="Yukon"></brand>
	<brand name="iRay"></brand>
	<brand name="Без бренда"></brand>
	<brand name="Другой"></brand>
	<brand name="Пилад"></brand>
</Optika_i_snaryazhenie>