<B2b_katalog_rukava_vysokogo_davleniya>
	<proizvoditel_rvd name="Alfagomma"></proizvoditel_rvd>
	<proizvoditel_rvd name="Comet"></proizvoditel_rvd>
	<proizvoditel_rvd name="Dunlop"></proizvoditel_rvd>
	<proizvoditel_rvd name="Flesstubo"></proizvoditel_rvd>
	<proizvoditel_rvd name="Galaxy"></proizvoditel_rvd>
	<proizvoditel_rvd name="Gates"></proizvoditel_rvd>
	<proizvoditel_rvd name="Heiberg"></proizvoditel_rvd>
	<proizvoditel_rvd name="Himpt"></proizvoditel_rvd>
	<proizvoditel_rvd name="HydraulicUnit"></proizvoditel_rvd>
	<proizvoditel_rvd name="IMM"></proizvoditel_rvd>
	<proizvoditel_rvd name="IVG"></proizvoditel_rvd>
	<proizvoditel_rvd name="Manuli"></proizvoditel_rvd>
	<proizvoditel_rvd name="Parker"></proizvoditel_rvd>
	<proizvoditel_rvd name="Premium"></proizvoditel_rvd>
	<proizvoditel_rvd name="SEL"></proizvoditel_rvd>
	<proizvoditel_rvd name="Sempercold"></proizvoditel_rvd>
	<proizvoditel_rvd name="Semperit"></proizvoditel_rvd>
	<proizvoditel_rvd name="Titan Lock"></proizvoditel_rvd>
	<proizvoditel_rvd name="Verso"></proizvoditel_rvd>
	<proizvoditel_rvd name="ZEC"></proizvoditel_rvd>
	<proizvoditel_rvd name="Завод гидрокомплект"></proizvoditel_rvd>
	<proizvoditel_rvd name="Манкупер"></proizvoditel_rvd>
	<proizvoditel_rvd name="Сварог"></proizvoditel_rvd>
	<proizvoditel_rvd name="Сервис Кар"></proizvoditel_rvd>
</B2b_katalog_rukava_vysokogo_davleniya>